README.md
setup.py
parsers/__init__.py
parsers/parser_factory.py
parsers/json/__init__.py
parsers/json/json_parser.py
parsers/json/source.py
parsers/src/__init__.py
parsers/src/constants.py
parsers/src/serialize_functions.py
parsers/toml/__init__.py
parsers/toml/source.py
parsers/toml/toml_parser.py
parsers/yaml/__init__.py
parsers/yaml/source.py
parsers/yaml/yaml_parser.py
tars_serialization_deserialization.egg-info/PKG-INFO
tars_serialization_deserialization.egg-info/SOURCES.txt
tars_serialization_deserialization.egg-info/dependency_links.txt
tars_serialization_deserialization.egg-info/top_level.txt
tests/__init__.py
tests/serialize_functions_test.py
tests/test_functions.py
tests/test_objects.py