Metadata-Version: 2.1
Name: tars-serialization-deserialization
Version: 0.1.2
Summary: library for python serialization
Home-page: https://github.com/ACC-Stas/Python-Labs
Author: Tarasenko Fyodor
Author-email: tarasenkafiodar@gmail.com
License: UNKNOWN
Platform: UNKNOWN
Classifier: Intended Audience :: Developers
Classifier: Programming Language :: Python
Classifier: Programming Language :: Python :: 3.9
Classifier: Operating System :: OS Independent
